[
  {
    "name": "mongo-php-library",
    "language": "PHP",
    "type": "Driver",
    "repo": "mongodb/mongo-php-library",
    "npm": null,
    "nuget": null,
    "rubygems": null,
    "crates": null,
    "pypi": null,
    "maven": null,
    "stars": 1613,
    "forks": 263,
    "contributors_count": 52,
    "closed_issues": 0,
    "avg_pr_merge_days": 4.361749999999998,
    "merged_prs_last_6mo": 77,
    "releases_count": 64,
    "release_frequency_per_year": 5.7301986852032005,
    "stackoverflow_total_questions": 175978,
    "stackoverflow_recent_questions_last_6mo": 130,
    "discussions_count": 0,
    "discussions_recent_activity_last_6mo": 0,
    "weekly_downloads": 1219840,
    "dependents": 22322,
    "index": 6.361138,
    "timestamp": "2026-03-15T05:14:59.367Z"
  }
]